{"version":1,"resource":"file:///c%3A/Users/n0ctu/Desktop/t.html","entries":[{"id":"USaC.html","source":"textFileCreate.source","timestamp":1700673064571},{"id":"UPL0.html","timestamp":1700673066712},{"id":"KngB.html","timestamp":1701354731660},{"id":"UMxr.html","timestamp":1701354743938},{"id":"tAsY.html","timestamp":1701354784304},{"id":"w2t4.html","timestamp":1701355086552},{"id":"Dle3.html","timestamp":1701786872658},{"id":"OZRt.html","timestamp":1701786887007},{"id":"h5qX.html","timestamp":1701786914989},{"id":"9HJP.html","timestamp":1701786955147},{"id":"zAAH.html","timestamp":1701787018486},{"id":"UTHV.html","source":"undoRedo.source","timestamp":1701787072040},{"id":"rHsd.html","timestamp":1701787099722},{"id":"YQ4i.html","timestamp":1701787120885},{"id":"VBTc.html","timestamp":1701787171994},{"id":"UJit.html","timestamp":1701787189121},{"id":"BFTF.html","timestamp":1701787204751},{"id":"9TjK.html","timestamp":1701787293832},{"id":"6PZx.html","timestamp":1701787494349},{"id":"73lc.html","timestamp":1701789418563},{"id":"QW1F.html","source":"undoRedo.source","timestamp":1701789431143}]}